pai_parser/__init__.py
pai_parser/grouper.py
pai_parser/parser.py
pai_parser/slicer.py
pai_parser/tokenizer.py
pai_parser-0.0.2.dist-info/DESCRIPTION.rst
pai_parser-0.0.2.dist-info/LICENSE.txt
pai_parser-0.0.2.dist-info/METADATA
pai_parser-0.0.2.dist-info/RECORD
pai_parser-0.0.2.dist-info/WHEEL
pai_parser-0.0.2.dist-info/metadata.json
pai_parser-0.0.2.dist-info/top_level.txt
